{
	"credit": "Made with Blockbench",
	"textures": {
		"0": "blocks/frosted_ice_0",
		"particle": "blocks/frosted_ice_0"
	},
	"elements": [
		{
			"from": [3, 5, 3],
			"to": [13, 15, 13],
			"faces": {
				"north": {"uv": [0, 0, 10, 10], "texture": "#0"},
				"east": {"uv": [0, 0, 10, 10], "texture": "#0"},
				"south": {"uv": [0, 0, 10, 10], "texture": "#0"},
				"west": {"uv": [0, 0, 10, 10], "texture": "#0"},
				"up": {"uv": [0, 0, 10, 10], "texture": "#0"},
				"down": {"uv": [0, 0, 10, 10], "texture": "#0"}
			}
		},
		{
			"from": [3, 11, 7],
			"to": [5, 13, 17],
			"rotation": {"angle": 45, "axis": "y", "origin": [7, 11, -1]},
			"faces": {
				"north": {"uv": [0, 0, 2, 2], "texture": "#0"},
				"east": {"uv": [0, 0, 10, 2], "texture": "#0"},
				"south": {"uv": [0, 0, 2, 2], "texture": "#0"},
				"west": {"uv": [0, 0, 10, 2], "texture": "#0"},
				"up": {"uv": [0, 0, 2, 10], "texture": "#0"},
				"down": {"uv": [0, 0, 2, 10], "texture": "#0"}
			}
		},
		{
			"from": [3, 8, -4],
			"to": [5, 10, 6],
			"rotation": {"angle": 22.5, "axis": "y", "origin": [7, 11, -1]},
			"faces": {
				"north": {"uv": [0, 0, 2, 2], "texture": "#0"},
				"east": {"uv": [0, 0, 10, 2], "texture": "#0"},
				"south": {"uv": [0, 0, 2, 2], "texture": "#0"},
				"west": {"uv": [0, 0, 10, 2], "texture": "#0"},
				"up": {"uv": [0, 0, 2, 10], "texture": "#0"},
				"down": {"uv": [0, 0, 2, 10], "texture": "#0"}
			}
		},
		{
			"from": [7, 16, -5],
			"to": [9, 18, 5],
			"rotation": {"angle": 45, "axis": "x", "origin": [7, 11, -1]},
			"faces": {
				"north": {"uv": [0, 0, 2, 2], "texture": "#0"},
				"east": {"uv": [0, 0, 10, 2], "texture": "#0"},
				"south": {"uv": [0, 0, 2, 2], "texture": "#0"},
				"west": {"uv": [0, 0, 10, 2], "texture": "#0"},
				"up": {"uv": [0, 0, 2, 10], "texture": "#0"},
				"down": {"uv": [0, 0, 2, 10], "texture": "#0"}
			}
		},
		{
			"from": [4, 8, 10],
			"to": [6, 18, 12],
			"rotation": {"angle": 45, "axis": "x", "origin": [7, 12, -1]},
			"faces": {
				"north": {"uv": [0, 0, 2, 10], "rotation": 180, "texture": "#0"},
				"east": {"uv": [0, 0, 10, 2], "rotation": 270, "texture": "#0"},
				"south": {"uv": [0, 0, 2, 10], "texture": "#0"},
				"west": {"uv": [0, 0, 10, 2], "rotation": 90, "texture": "#0"},
				"up": {"uv": [0, 0, 2, 2], "rotation": 180, "texture": "#0"},
				"down": {"uv": [0, 0, 2, 2], "texture": "#0"}
			}
		},
		{
			"from": [4, 2, 6],
			"to": [6, 4, 16],
			"rotation": {"angle": -45, "axis": "x", "origin": [7, 11, -1]},
			"faces": {
				"north": {"uv": [0, 0, 2, 2], "texture": "#0"},
				"east": {"uv": [0, 0, 10, 2], "texture": "#0"},
				"south": {"uv": [0, 0, 2, 2], "texture": "#0"},
				"west": {"uv": [0, 0, 10, 2], "texture": "#0"},
				"up": {"uv": [0, 0, 2, 10], "texture": "#0"},
				"down": {"uv": [0, 0, 2, 10], "texture": "#0"}
			}
		},
		{
			"from": [-3, 8, 6],
			"to": [7, 10, 8],
			"rotation": {"angle": -22.5, "axis": "z", "origin": [7, 11, -1]},
			"faces": {
				"north": {"uv": [0, 0, 2, 10], "rotation": 270, "texture": "#0"},
				"east": {"uv": [0, 0, 2, 2], "rotation": 90, "texture": "#0"},
				"south": {"uv": [0, 0, 2, 10], "rotation": 270, "texture": "#0"},
				"west": {"uv": [0, 0, 2, 2], "rotation": 270, "texture": "#0"},
				"up": {"uv": [0, 0, 10, 2], "texture": "#0"},
				"down": {"uv": [0, 0, 10, 2], "rotation": 180, "texture": "#0"}
			}
		}
	],
	"display": {
		"head": {
			"translation": [0, -50, 0]
		}
	},
	"groups": [
		{
			"name": "stone_hoe_2",
			"origin": [8, 8, 8],
			"children": [0, 1, 2, 3, 4, 5, 6]
		}
	]
}